{"id": "3186882", "date": "2020-12-31T23:04:13+00:00", "user": "FAT32", "post": "\n<div class=\"Message userContent\">\n<blockquote class=\"UserQuote\"><div class=\"QuoteText\">\n<p><a href=\"https://www.lowendtalk.com/profile/cociu\" rel=\"nofollow\">@cociu</a> said:<br>\nNekki this go for you <a href=\"https://imgur.com/a/qUvcKc3\" rel=\"nofollow\">https://imgur.com/a/qUvcKc3</a> happy new year !</p>\n</div></blockquote>\n<p>Love is the only thing that can transcend time and space <img class=\"emoji\" src=\"https://www.lowendtalk.com/resources/emoji/joy.png\" title=\":joy:\" alt=\":joy:\" height=\"20\"></p>\n</div>\n"}